setup.py
django_runner/__init__.py
django_runner.egg-info/PKG-INFO
django_runner.egg-info/SOURCES.txt
django_runner.egg-info/dependency_links.txt
django_runner.egg-info/requires.txt
django_runner.egg-info/top_level.txt
django_runner/management/__init__.py
django_runner/management/commands/__init__.py
django_runner/management/commands/runner.py