Metadata-Version: 1.0
Name: django-runner
Version: 0.1.1
Summary: Run arbitrary script within Django environment
Home-page: https://github.com/eagletmt/django-runner
Author: Kohei Suzuki
Author-email: eagletmt@gmail.com
License: MIT
Platform: UNKNOWN
